{"@module": "pydefect.analyzer.band_edge_states", "@class": "PerfectBandEdgeState", "@version": "0.9.1", "vbm_info": {"@module": "pydefect.analyzer.band_edge_states", "@class": "EdgeInfo", "@version": "0.9.1", "band_idx": 1349, "kpt_coord": [0.0, 0.0, 0.0], "orbital_info": {"@module": "pydefect.analyzer.band_edge_states", "@class": "OrbitalInfo", "@version": "0.9.1", "energy": 5.2445, "orbitals": {"Ga": [0.0, 0.0, 0.15], "N": [0.0, 0.6, 0.0]}, "occupation": 1.0, "participation_ratio": null}}, "cbm_info": {"@module": "pydefect.analyzer.band_edge_states", "@class": "EdgeInfo", "@version": "0.9.1", "band_idx": 1350, "kpt_coord": [0.0, 0.0, 0.0], "orbital_info": {"@module": "pydefect.analyzer.band_edge_states", "@class": "OrbitalInfo", "@version": "0.9.1", "energy": 7.0851, "orbitals": {"Ga": [0.3, 0.0, 0.0], "N": [0.3, 0.0, 0.0]}, "occupation": 0.0, "participation_ratio": null}}}